simplews/__about__.py
simplews/__init__.py
simplews/client.py
simplews/server.py
simplews/ws.py
simple_websockets-0.1.0.dist-info/METADATA
simple_websockets-0.1.0.dist-info/WHEEL
simple_websockets-0.1.0.dist-info/licenses/LICENSE.txt
simple_websockets-0.1.0.dist-info/RECORD
