Metadata-Version: 2.1
Name: simple-websockets
Version: 0.1.0
Summary: Simple websocket server and client with callback-based API.
Project-URL: Documentation, https://github.com/xuanzhi33/simple-websockets#readme
Project-URL: Issues, https://github.com/xuanzhi33/simple-websockets/issues
Project-URL: Source, https://github.com/xuanzhi33/simple-websockets
Author-email: xuanzhi33 <xuanzhi33@qq.com>
License-Expression: GPL-3.0-only
License-File: LICENSE.txt
Classifier: Development Status :: 4 - Beta
Classifier: Programming Language :: Python
Classifier: Programming Language :: Python :: 3.8
Classifier: Programming Language :: Python :: 3.9
Classifier: Programming Language :: Python :: 3.10
Classifier: Programming Language :: Python :: 3.11
Classifier: Programming Language :: Python :: 3.12
Classifier: Programming Language :: Python :: Implementation :: CPython
Classifier: Programming Language :: Python :: Implementation :: PyPy
Requires-Python: >=3.8
Requires-Dist: websockets
